README.rst
setup.py
cssconflict/__init__.py
cssconflict.egg-info/PKG-INFO
cssconflict.egg-info/SOURCES.txt
cssconflict.egg-info/dependency_links.txt
cssconflict.egg-info/entry_points.txt
cssconflict.egg-info/not-zip-safe
cssconflict.egg-info/requires.txt
cssconflict.egg-info/top_level.txt