Metadata-Version: 1.1
Name: cssconflict
Version: 0.1.2
Summary: css coflict checking
Home-page: https://github.com/podhmo/cssconflict
Author: podhmo
Author-email: UNKNOWN
License: UNKNOWN
Keywords: css,cssdiff,cssconflict
Platform: UNKNOWN
Classifier: Programming Language :: Python
Classifier: Programming Language :: Python :: Implementation :: CPython
